Metadata-Version: 1.0
Name: gb-ali-distributions
Version: 0.1
Summary: Gaussian distributions and Binomial distributions
Home-page: UNKNOWN
Author: UNKNOWN
Author-email: liaquat85@gmail.com
License: UNKNOWN
Platform: UNKNOWN
